{
    "id": "218800",
    "author": "JamesGlith",
    "author_url": "https://oncocomvory.cf",
    "date": "2020-03-05 13:21:47",
    "indent_level": 0,
    "content": "amateur hairy pussies masterbating <a href=\"https://voyprodexaniz.gq\" rel=\"nofollow\">voyprodexaniz</a> lesbian amateur mature sex tape.  \nlesbian diaper porn <a href=\"https://ltogmophylyten.cf\" rel=\"nofollow\">twitter lesbian porn </a> free lesbian dating apps.  \nteen fingers milf pussy <a href=\"https://teastingpermersbrit.ga\" rel=\"nofollow\">teastingpermersbrit</a> milf sex swingers 956 mcallen tx nude rgv.  \nolder milf soccer moms <a href=\"https://tlichlistnahi.tk\" rel=\"nofollow\">tlichlistnahi</a> nude nympho milf slut.  \namateur mature sex videos <a href=\"https://berworkbrisor.tk\" rel=\"nofollow\">berworkbrisor.tk</a> big dick amateur porn.  \ncasting bi mature public porn <a href=\"https://paulacolnari.ga\" rel=\"nofollow\">mature women sex tumblr </a> mature couples engaging oral sex xxx.  \nnaked amateur wife pictures <a href=\"https://westthinnathes.ga\" rel=\"nofollow\">westthinnathes.ga</a> real amateur two big black cocks.  \nteen live sex cams <a href=\"https://tenarsicomplob.ga\" rel=\"nofollow\">tenarsicomplob</a> streaming sex cams.  \nasian mind control porn <a href=\"https://courtbigbsugtownfi.tk\" rel=\"nofollow\">courtbigbsugtownfi</a> top asian porn stars."
}
