{
    "id": "225688",
    "author": "unxhhEmeby",
    "author_url": "https://pharm-usa-official.com",
    "date": "2020-03-31 14:43:30",
    "indent_level": 0,
    "content": "overdosed on viagra tombstone  can women take viagra  <a href=\"https://pharm-usa-official.com/# #\" rel=\"nofollow\">cheap viagra  </a>  viagra coupon  eception form for viagra \n \nviagra 200mg  how does viagra work  <a href=\"https://pharm-usa-official.com/#\" rel=\"nofollow\">viagra side effects </a>  amateur homemade sex viagra  penis on viagra before after \n \nhttps://pharm-usa-official.com - viagra online \n \nhttp://www.archiwum.info.kety.pl/index.php?view=detail&amp;id=242&amp;option=com_joomgallery\nhttps://www.kortnimarie.com/2015/02/11/casa-lantana-wedding-anthony-dana/?unapproved=295211&amp;moderation-hash=3a59828ad9066c081899c11a5da96e96#comment-295211\nhttp://iamgalla.com/2012/10/galla-takes-colorado-1/?unapproved=7506587&amp;moderation-hash=c7c6baaf22d75ae4e0903d8be19e3511#comment-7506587\nhttps://acessocultural.com.br/2020/01/marighella-de-wagner-moura-tem-estreia-confirmada-nos-cinemas/?unapproved=530768&amp;moderation-hash=959a7ce6e576e63b8a4ea19202a24243#comment-530768\nhttps://lcfwines.com/goosecross-october-01-2014137-2/?unapproved=208357&amp;moderation-hash=8632cd8932a6ee94d7fe588ce088f830#comment-208357"
}
