{
    "id": "465",
    "author": "Gabi Pagliuca",
    "author_url": "http://www.blogger.com/profile/12779019605376440114",
    "date": "2010-04-14 05:59:18",
    "indent_level": 0,
    "content": "oi? Isaque? Eh vc? Mano, tão comentando no seu nome. Só pode hahahahahaha. Como assim moh texto tenso e profundo e vc comenta \"OWN\" e dps  \"qro bjar\"? Hahahahahahahaha. Eh pq eu fico insistindo, né?! Ok, não vou mais obrigar vc a comentar. Mas dps não vai querer fala cmg sobre o texto por msn hauhaauahauhauahau<br /><br /><br />Um beijo camarada!"
}
