{
    "id": "494",
    "author": "Gabi Pagliuca",
    "author_url": "http://www.blogger.com/profile/12779019605376440114",
    "date": "2010-05-31 00:09:10",
    "indent_level": 0,
    "content": "Alguma coisa tem, a personagem só não sabe definir, acho que nessa passagem: \"De vez em quando até me iludo quando pede pra eu ficar mais ou me leva pra casa dirigindo com uma mão no meu joelho e diz que comigo que é bom estar... \"  diz bem que algo eles tinham, pois talvez seja isso que ela não queira perder 🙂<br /><br />Obrigada por ler e comentar<br /><br />Beijos<br /><br />Gabi"
}
