{
    "id": "212872",
    "author": "Williedup",
    "author_url": "",
    "date": "2020-02-15 04:04:56",
    "indent_level": 0,
    "content": "examples of a leadership development plan essay <a href=\"https://brenintanduthe.gq\" rel=\"nofollow\">brenintanduthe.gq</a> how to adress the hypothesis in the essay.  \nvoyeur cam toilet <a href=\"https://mingzicomprigar.ga\" rel=\"nofollow\">mingzicomprigar.ga</a> and get chatting teen chat.  \nmolly stewart porn lesbian <a href=\"https://quagmalachoore.cf\" rel=\"nofollow\">quagmalachoore.cf</a> amateur first lesbian sex.  \nforced the lesbian way porn straight <a href=\"https://mortmislotecle.cf\" rel=\"nofollow\">baked bbw lesbians sex </a> extreme ebony lesbian porn. ] \nhow to annotate a website in the essay <a href=\"https://norrdumatofin.tk\" rel=\"nofollow\">essay writing for 7th graders </a> good persuasive essay topics for elementary school.  \nfree sex clip camel <a href=\"https://priminclenew.tk\" rel=\"nofollow\">priminclenew.tk</a> video webcam teen hairy armpits.  \ndelete profile on christian dating for free <a href=\"https://stinfoperfca.tk\" rel=\"nofollow\">totally free asian dating sites </a> who is chase from chrisley knows best dating.  \nlesbians porn xxx <a href=\"https://frisaltonli.tk\" rel=\"nofollow\">ella hughes lesbian strapon femdom </a> lesbian group sex porn movies."
}
