{
    "id": "218352",
    "author": "JamesGlith",
    "author_url": "https://wheelswingdownriren.ml",
    "date": "2020-03-04 03:43:27",
    "indent_level": 0,
    "content": "the man who was almost a man analysis essay <a href=\"https://tzatosnovo.tk\" rel=\"nofollow\">tzatosnovo</a> how many words in my essay.  \nblack teen sucking white cock <a href=\"https://remptermyga.tk\" rel=\"nofollow\">remptermyga.tk</a> white men sucking black cock video.  \nlive milf sex cams <a href=\"https://berdobepins.ml\" rel=\"nofollow\">online sex cams free </a> male sex cams.  \nuk dating site <a href=\"https://forsetpsuppsi.cf\" rel=\"nofollow\">forsetpsuppsi.cf</a> match.com search login.  \nreal hookup sites that work <a href=\"https://laubrochustvimo.gq\" rel=\"nofollow\">free adult sex personals </a> meetup dating.  \nblack actors japanese porn <a href=\"https://cerecorype.cf\" rel=\"nofollow\">ebony teen porn movies </a> black girls white guy porn.  \nchubby mature ass fucking <a href=\"https://pulcwebctalga.tk\" rel=\"nofollow\">pulcwebctalga.tk</a> amateur mature mother son breeding videos tumblr.  \npersonal essay about yourself examples <a href=\"https://tzatosnovo.tk\" rel=\"nofollow\">tzatosnovo.tk</a> comparison and contrast essay examples free.  \nmilfs sucking black dicks <a href=\"https://rahungaba.tk\" rel=\"nofollow\">rahungaba.tk</a> black girls pussy pictures."
}
