{
    "id": "234801",
    "author": "zflnogDusly",
    "author_url": "http://pharm-usa-official.com/",
    "date": "2020-04-22 05:23:16",
    "indent_level": 0,
    "content": "viagra generic  viagra vs cialis  <a href=\"http://pharm-usa-official.com/#\" rel=\"nofollow\">buy viagra online</a>  side effects for viagra  hims viagra \n \nfree viagra  viagra for men  <a href=\"http://pharm-usa-official.com/#\" rel=\"nofollow\"> buy viagra online</a>  how does viagra work  generic viagra available \n \nhttp://pharm-usa-official.com/#  - viagra generic"
}
