{
    "id": "532",
    "author": "Isaque Criscuolo",
    "author_url": "http://www.blogger.com/profile/04520355472989946006",
    "date": "2010-10-29 12:11:11",
    "indent_level": 0,
    "content": "É muito mais fácil aceitar o que a mídia produz e \"engolir\" tudo isso do que destrinchar a informação e procurar a verdadeira VERDADE. Se é que ela existe. <br />A TV e a maioria dos grandes veículos de informação manipulam seu público desde que a humanidade é humanidade. Infelizmente, poucos resistiram a essa manipulação e conseguiram conscientizar o povo. <br />Me sinto na liberdade de comparar a mídia com as religiões, sempre definindo pontos de vista, carregando uma massa que não pensa e segue o rebanho. <br />O que precisamos é de consciência política, consciência do que lemos, consciência do que pensamos e achamos do mundo. É o que você disse, precisamos refletir, buscar o NOSSO ponto de vista.<br />Existiram muitas pessoas que mudaram o mundo com seu ponto de vista. E você, Pagliuca, é uma das grandes pessoas que tem mudado minha vida e  realidade, me ajudando a encontrar as infinitas possibilidades de assuntos e perspectivas de compreensão. Belíssimo texto. =D"
}
