{
    "id": "238221",
    "author": "otaletldbu",
    "author_url": "http://ketofections.com/groups/cost-of-viagra-without-insurance-631816",
    "date": "2020-04-28 00:21:25",
    "indent_level": 0,
    "content": "<a href=\"http://vintagepaper.store/groups/viagra-einzeln-online-kaufen-662062\" rel=\"nofollow\">link</a> <a href=\"http://www.mydogs.us/groups/viagra-30-pills-706919\" rel=\"nofollow\">link</a> <a href=\"http://metoyoubag.com/forums/users/ketriasoeperna/\" rel=\"nofollow\">link</a> <a href=\"http://papacornercoaching.com/forums/users/ketriasoeperna/\" rel=\"nofollow\">link</a> <a href=\"http://l-chika.com/forums/users/ketriasoeperna/\" rel=\"nofollow\">link</a> <a href=\"http://reliablerealestateinc.com/groups/online-cialis-purchase-870343\" rel=\"nofollow\">link</a> <a href=\"http://blackwitchcoven.com.au/forums/users/ketriasoeperna/\" rel=\"nofollow\">link</a> <a href=\"http://msf-adelberg.de/forums/users/ketriasoeperna/\" rel=\"nofollow\">link</a> <a href=\"http://blogdetodas.com/forums/user/ketriasoeperna/\" rel=\"nofollow\">link</a> <a href=\"http://reliablerealestateinc.com/groups/best-place-to-buy-generic-viagra-online-115186\" rel=\"nofollow\">link</a> <a href=\"http://carouse.life/groups/how-safe-is-generic-viagra-771071\" rel=\"nofollow\">link</a> <a href=\"http://www.intercp.org/forums/users/ketriasoeperna/\" rel=\"nofollow\">link</a> <a href=\"http://trgpdild.com/groups/online-pharmacy-for-cialis-392153\" rel=\"nofollow\">link</a> <a href=\"http://lewebmag.com/forums/users/ketriasoeperna/\" rel=\"nofollow\">link</a> <a href=\"http://ketofections.com/groups/40mg-cialis-online-642815\" rel=\"nofollow\">link</a> <a href=\"http://swnut77.com/forums/users/ketriasoeperna/\" rel=\"nofollow\">link</a> <a href=\"http://attorneyetal.com/groups/buy-cialis-professional-cheap-519157\" rel=\"nofollow\">link</a> <a href=\"http://demoozarksrobotics.com/forums/users/ketriasoeperna/\" rel=\"nofollow\">link</a> <a href=\"http://biztektoolbox.com/groups/viagra-professional-180-pills-102070\" rel=\"nofollow\">link</a> <a href=\"http://mykooiker.com/groups/female-viagra-online-canada-347825\" rel=\"nofollow\">link</a> <a href=\"http://member-lab.com/forums/user/ketriasoeperna/\" rel=\"nofollow\">link</a> <a href=\"http://digitalfootprint.us/forums/users/ketriasoeperna/\" rel=\"nofollow\">link</a> <a href=\"http://lessontoday.com/groups/cialis-italiano-online-628160\" rel=\"nofollow\">link</a> <a href=\"http://isciac.pt/forums/users/ketriasoeperna/\" rel=\"nofollow\">link</a> <a href=\"http://www.hoop-ball.com/forums/users/ketriasoeperna/\" rel=\"nofollow\">link</a>  42324523422453234"
}
