{
    "id": "285272",
    "author": "ofxaabx",
    "author_url": "https://market.kolyma.ru/user/profile/281012",
    "date": "2020-06-29 10:03:09",
    "indent_level": 0,
    "content": "5412430 335225849 \n \nhttps://market.kolyma.ru/user/profile/264960 https://market.kolyma.ru/user/profile/266665 https://market.kolyma.ru/user/profile/266665 https://market.kolyma.ru/user/profile/268695 https://market.kolyma.ru/user/profile/268695 https://market.kolyma.ru/user/profile/269506 https://market.kolyma.ru/user/profile/269506 https://market.kolyma.ru/user/profile/269506 https://market.kolyma.ru/user/profile/269506 https://market.kolyma.ru/user/profile/269506 https://market.kolyma.ru/user/profile/269506 https://market.kolyma.ru/user/profile/269506 https://market.kolyma.ru/user/profile/269506 https://market.kolyma.ru/user/profile/269506 https://market.kolyma.ru/user/profile/269506 https://market.kolyma.ru/user/profile/269506 https://market.kolyma.ru/user/profile/269506 https://market.kolyma.ru/user/profile/269506 https://market.kolyma.ru/user/profile/269506 https://market.kolyma.ru/user/profile/269506 https://market.kolyma.ru/user/profile/270583 https://market.kolyma.ru/user/profile/270583 https://market.kolyma.ru/user/profile/270583 https://market.kolyma.ru/user/profile/270583 https://market.kolyma.ru/user/profile/270583 https://market.kolyma.ru/user/profile/270583 https://market.kolyma.ru/user/profile/270583 https://market.kolyma.ru/user/profile/270703 https://market.kolyma.ru/user/profile/270703 https://market.kolyma.ru/user/profile/270703 https://market.kolyma.ru/user/profile/270703 https://market.kolyma.ru/user/profile/270703 https://market.kolyma.ru/user/profile/270703 https://market.kolyma.ru/user/profile/271387 https://market.kolyma.ru/user/profile/271387 https://market.kolyma.ru/user/profile/271387 https://market.kolyma.ru/user/profile/271387 https://market.kolyma.ru/user/profile/271387 https://market.kolyma.ru/user/profile/271387 https://market.kolyma.ru/user/profile/271387 https://market.kolyma.ru/user/profile/271387 https://market.kolyma.ru/user/profile/271405 https://market.kolyma.ru/user/profile/271405 https://market.kolyma.ru/user/profile/271405 https://market.kolyma.ru/user/profile/271405 https://market.kolyma.ru/user/profile/271405 https://market.kolyma.ru/user/profile/271405 https://market.kolyma.ru/user/profile/274347 https://market.kolyma.ru/user/profile/274347 https://market.kolyma.ru/user/profile/274347 https://market.kolyma.ru/user/profile/274347 https://market.kolyma.ru/user/profile/274347 https://market.kolyma.ru/user/profile/274347 https://market.kolyma.ru/user/profile/274347 https://market.kolyma.ru/user/profile/274419 https://market.kolyma.ru/user/profile/274419 https://market.kolyma.ru/user/profile/274419 https://market.kolyma.ru/user/profile/274419 https://market.kolyma.ru/user/profile/274630 https://market.kolyma.ru/user/profile/274630 https://market.kolyma.ru/user/profile/277392 https://market.kolyma.ru/user/profile/277431 https://market.kolyma.ru/user/profile/277431 https://market.kolyma.ru/user/profile/277431 https://market.kolyma.ru/user/profile/277462 https://market.kolyma.ru/user/profile/277462 https://market.kolyma.ru/user/profile/277462 https://market.kolyma.ru/user/profile/277462 https://market.kolyma.ru/user/profile/277462 https://market.kolyma.ru/user/profile/277468 https://market.kolyma.ru/user/profile/277468 https://market.kolyma.ru/user/profile/277468 https://market.kolyma.ru/user/profile/277468 https://market.kolyma.ru/user/profile/277468 https://market.kolyma.ru/user/profile/277468 https://market.kolyma.ru/user/profile/277919 https://market.kolyma.ru/user/profile/277919 https://market.kolyma.ru/user/profile/277919 https://market.kolyma.ru/user/profile/277919 https://market.kolyma.ru/user/profile/277919 https://market.kolyma.ru/user/profile/277919 https://market.kolyma.ru/user/profile/277919 https://market.kolyma.ru/user/profile/277919 https://market.kolyma.ru/user/profile/277979 https://market.kolyma.ru/user/profile/278037 https://market.kolyma.ru/user/profile/278037 https://market.kolyma.ru/user/profile/278037 https://market.kolyma.ru/user/profile/278037 https://market.kolyma.ru/user/profile/278037 https://market.kolyma.ru/user/profile/278037 https://market.kolyma.ru/user/profile/278037 https://market.kolyma.ru/user/profile/278037 https://market.kolyma.ru/user/profile/278037 https://market.kolyma.ru/user/profile/278037 https://market.kolyma.ru/user/profile/278037 https://market.kolyma.ru/user/profile/278037 https://market.kolyma.ru/user/profile/278716 https://market.kolyma.ru/user/profile/278819 https://market.kolyma.ru/user/profile/278819 https://market.kolyma.ru/user/profile/278819 https://market.kolyma.ru/user/profile/278819 https://market.kolyma.ru/user/profile/278819 https://market.kolyma.ru/user/profile/278819 https://market.kolyma.ru/user/profile/278864 https://market.kolyma.ru/user/profile/278864 https://market.kolyma.ru/user/profile/278864 https://market.kolyma.ru/user/profile/278864 https://market.kolyma.ru/user/profile/278864 https://market.kolyma.ru/user/profile/278932 https://market.kolyma.ru/user/profile/280284 https://market.kolyma.ru/user/profile/280525 https://market.kolyma.ru/user/profile/280525 https://market.kolyma.ru/user/profile/280525 https://market.kolyma.ru/user/profile/280525 https://market.kolyma.ru/user/profile/280525 https://market.kolyma.ru/user/profile/280525 https://market.kolyma.ru/user/profile/280525 https://market.kolyma.ru/user/profile/280525 https://market.kolyma.ru/user/profile/280525 https://market.kolyma.ru/user/profile/280525 https://market.kolyma.ru/user/profile/280525 https://market.kolyma.ru/user/profile/280525 https://market.kolyma.ru/user/profile/281012 https://market.kolyma.ru/user/profile/281012 https://market.kolyma.ru/user/profile/281012"
}
