{
    "id": "233820",
    "author": "grrpoEmeby",
    "author_url": "https://www.fresher.ru/elz",
    "date": "2020-04-20 10:10:28",
    "indent_level": 0,
    "content": "how to make money online from home  how to make money quick  <a href=\"https://www.fresher.ru/elz/\" rel=\"nofollow\">make money online</a>  how does venmo make money  make money online fast \n \nhow does facebook make money  make money from home  <a href=\"https://www.fresher.ru/elz/\" / rel=\"nofollow\"> make money</a>  how to make money at home  woodworking ideas to make money \n \nhttps://www.fresher.ru/elz/  - make money"
}
