{
    "id": "96982",
    "author": "lungrecvelm",
    "author_url": "https://www.drive2.ru/b/519012370337497160/",
    "date": "2019-01-18 10:49:03",
    "indent_level": 0,
    "content": "Присоединяюсь. Так бывает. Можем пообщаться на эту тему.\n \n--- \nда смеюсь я, смеюсь товары почтой посуда, товары почтой тв или <a href=\"https://www.drive2.ru/b/518748762424738574/\" / rel=\"nofollow\">источник</a> каталог товара почта \n<a href=\"https://www.drive2.ru/b/518758932907295169/\" / rel=\"nofollow\">на этом сайте</a>\n<a href=\"https://www.drive2.ru/b/518909840878207851/\" / rel=\"nofollow\">продолжение</a>\n<a href=\"https://www.drive2.ru/b/518987356447966035/\" / rel=\"nofollow\">продолжение</a>\n<a href=\"https://www.drive2.ru/b/518963716947968229/\" / rel=\"nofollow\">тут</a>\n<a href=\"https://www.drive2.ru/b/518879329430536967/\" / rel=\"nofollow\">источник</a>"
}
