{
    "id": "239387",
    "author": "Suzannafaow",
    "author_url": "http://tokarevka-adm.ru/bitrix/redirect.php?event1=&event2=&event3=&goto=http://viagra-generics.us",
    "date": "2020-04-30 01:54:24",
    "indent_level": 0,
    "content": "how long does viagra removes from body <a href=\"http://tk-elko.ru/bitrix/redirect.php?event1=&amp;event2=&amp;event3=&amp;goto=http://viagra-generics.us\" rel=\"nofollow\">online generic viagra</a> when do people start using viagra http://podonki.info/go.php?url=http://viagra-generics.us what doctor to see viagra [url=http://times.tj/redirect?url=http://viagra-generics.us]viagra for sale online[/url] http://tkt.ba/modules/babel/redirect.php?newlang=bs_BA&amp;newurl=http://viagra-generics.us how to make a boner last long without viagra \n \nhttp://solidbodyandsoul.org/__media__/js/netsoltrademark.php?d=viagra-generics.us \nhttp://everything-science.com/__media__/js/netsoltrademark.php?d=viagra-generics.us \nhttp://tutuandforgivenessfilm.org/__media__/js/netsoltrademark.php?d=viagra-generics.us \nhttp://smithbucklin.info/__media__/js/netsoltrademark.php?d=viagra-generics.us"
}
