{
    "id": "222197",
    "author": "AndrewElori",
    "author_url": "https://prepuniptog.ml",
    "date": "2020-03-20 10:04:08",
    "indent_level": 0,
    "content": "livr sex cams <a href=\"https://poavanrarid.tk\" rel=\"nofollow\">poavanrarid</a> free live nude sex cams.  \nbig black boobs pics <a href=\"https://comscompbanga.tk\" rel=\"nofollow\">comscompbanga</a> black and white pussy.  \namateur porn college party <a href=\"https://abblitartaso.ga\" rel=\"nofollow\">abblitartaso</a> amateur dont cum in me.  \nsex video you porn shemal lesbian <a href=\"https://chrisversioterri.ml\" rel=\"nofollow\">chrisversioterri.ml</a> long tongue lesbian porn.  \nbig tits amateur milf <a href=\"https://westthinnathes.ga\" rel=\"nofollow\">westthinnathes</a> amateur wife xxx gif.  \ncollege girls try out for anal sex <a href=\"https://confnickgehu.tk\" rel=\"nofollow\">confnickgehu.tk</a> amateur college girls ass.  \nteen porn stars in pigtails <a href=\"https://teastingpermersbrit.gq\" rel=\"nofollow\">teastingpermersbrit.gq</a> emilie teen goddess nude.  \nhot asian taxi sex gif <a href=\"https://tlecsorgamo.tk\" rel=\"nofollow\">big asian teen tits </a> japanese dildo dance porn.  \ndating for 20 year olds <a href=\"https://presanlalacon.tk\" rel=\"nofollow\">hong jin young dating </a> dating a broke guy."
}
