{
    "id": "218580",
    "author": "JasonPor",
    "author_url": "https://liluwalhand.gq",
    "date": "2020-03-04 21:00:04",
    "indent_level": 0,
    "content": "facebook dating site <a href=\"https://hindmarpetorlie.tk\" rel=\"nofollow\">hindmarpetorlie.tk</a> single parents meet review.  \namateur wife fucks two guys <a href=\"https://erlatilecra.tk\" rel=\"nofollow\">erlatilecra.tk</a> real amateurs having sex.  \nmilfs with big boobs <a href=\"https://ourcondere.tk\" rel=\"nofollow\">ourcondere.tk</a> black milf xxx videos.  \nquestions to ask online dating before meeting <a href=\"https://presanlalacon.gq\" rel=\"nofollow\">presanlalacon</a> sugar mummy dating site in usa.  \nhow to end a essay <a href=\"https://anculopen.ml\" rel=\"nofollow\">why do you deserve this scholarship essay example </a> graduate school essay sample."
}
