{
    "id": "251286",
    "author": "Hillaryanyp",
    "author_url": "http://lindamedic.com",
    "date": "2020-05-19 21:15:29",
    "indent_level": 0,
    "content": "viagra or cialis which is better <a href=\"https://www.24tm.ru:443/redirect?url=http://lindamedic.com\" rel=\"nofollow\">buy viagra</a> viagra levitra and cialis which one is more potent http://u.42.pl/index.php?url=http://lindamedic.com issue of grapefruit with viagra http://moskraeved.ru/redirect?url=https://lindamedic.com/ - viagra online http://ezproxy.cityu.edu.hk/login?url=https://lindamedic.com/ what is a viagra party \n \nhttp://haroldcard.com/__media__/js/netsoltrademark.php?d=lindamedic.com \nhttp://kooee.com/__media__/js/netsoltrademark.php?d=lindamedic.com \nhttp://paseoartsdistrict.net/__media__/js/netsoltrademark.php?d=lindamedic.com \nhttp://marketingtechinsites.com/__media__/js/netsoltrademark.php?d=lindamedic.com"
}
