{
    "id": "215140",
    "author": "Jamesgon",
    "author_url": "https://reedewhidebi.tk",
    "date": "2020-02-22 11:00:06",
    "indent_level": 0,
    "content": "free lesbian porn with toys <a href=\"https://nanighpresovtrac.ga\" rel=\"nofollow\">lesbian analingus ass lick </a> lesbian nude puba pussy clit.  \nhd mature porn videos <a href=\"https://intravlothickspec.ga\" rel=\"nofollow\">intravlothickspec</a> mature women that love sex.  \nfree real sex cams <a href=\"https://poavanrarid.tk\" rel=\"nofollow\">poavanrarid.tk</a> male sex cams.  \nbbc fuck college 2 girl <a href=\"https://liluwalhand.gq\" rel=\"nofollow\">liluwalhand.gq</a> lesbian videos college rule.  \ncauses of ww1 essay <a href=\"https://exapsuta.tk\" rel=\"nofollow\">exapsuta.tk</a> graduate school essay format."
}
