{
    "id": "220485",
    "author": "AndrewElori",
    "author_url": "https://rodiscrere.tk",
    "date": "2020-03-09 22:10:42",
    "indent_level": 0,
    "content": "sexy lesbians porn <a href=\"https://ltogmophylyten.cf\" rel=\"nofollow\">ltogmophylyten</a> ebony big clit lesbians.  \ndirty dating live <a href=\"https://ravalable.tk\" rel=\"nofollow\">top free adult sites </a> the best free dating sites.  \nchaturbate vibrator <a href=\"https://seizeltadis.cf\" rel=\"nofollow\">kaytcrush chaturbate </a> chaturbate pik4pik4.  \nabout me examples for dating sites <a href=\"https://umroluzehn.gq\" rel=\"nofollow\">umroluzehn.gq</a> e dating site.  \nap lang essay that scored 9 rhetorical analysis <a href=\"https://gutraicosavar.tk\" rel=\"nofollow\">definition essay on beauty </a> what is an evaluation essay.  \nasian nude teen ladyboys <a href=\"https://komicrethe.ml\" rel=\"nofollow\">komicrethe.ml</a> indian teen porn movies.  \nnaked teen tied up <a href=\"https://vieletdesynchco.ml\" rel=\"nofollow\">cum in teen pussy </a> nude indian teens hostel.  \nnude teens round ass <a href=\"https://npokmicnylptetu.ml\" rel=\"nofollow\">npokmicnylptetu.ml</a> teen pussy spreading pics.  \nhot college sex party <a href=\"https://crinpasbuzzdgadin.gq\" rel=\"nofollow\">tumblr amateur college girls </a> college guys with big cocks gang bang."
}
