{
    "id": "215161",
    "author": "Jamesgon",
    "author_url": "https://portneskontsedest.tk",
    "date": "2020-02-22 12:29:22",
    "indent_level": 0,
    "content": "x dating sites <a href=\"https://eransoursei.cf\" rel=\"nofollow\">eransoursei</a> vegetarian dating sites.  \nlatina lesbian porn stars <a href=\"https://aderesnan.tk\" rel=\"nofollow\">online lesbian sex games </a> big boob lesbian free sex.  \nsex finder app <a href=\"https://pealenpaurapu.ga\" rel=\"nofollow\">pealenpaurapu</a> legit adult dating sites.  \nkiittygoddess chaturbate <a href=\"https://avatbesysde.ga\" rel=\"nofollow\">avatbesysde.ga</a> chaturbate clone.  \namateur pet play porn <a href=\"https://righpathogo.tk\" rel=\"nofollow\">xxx little young amateur homemade tiny </a> freaky ebony amateur porn."
}
