{
    "id": "214777",
    "author": "Jamesgon",
    "author_url": "https://volkcurefe.tk",
    "date": "2020-02-21 11:33:58",
    "indent_level": 0,
    "content": "nude milfs in jeans <a href=\"https://inwarana.tk\" rel=\"nofollow\">inwarana</a> sage milf wife nude.  \nebony teen thot sex tubes <a href=\"https://pulpipepep.tk\" rel=\"nofollow\">young hairy black pussy </a> hairy naked black women.  \njapanese teen porn pics <a href=\"https://whatsrargetopo.tk\" rel=\"nofollow\">whatsrargetopo.tk</a> clothes on off teen naked pics.  \nfree dating sites for single parents <a href=\"https://fuddpocomatu.tk\" rel=\"nofollow\">fuddpocomatu.tk</a> ok c.  \nmiss black nude pageant <a href=\"https://uzinexsepor.gq\" rel=\"nofollow\">uzinexsepor.gq</a> black pussy licking good."
}
