{
    "id": "177172",
    "author": "Gregorypes",
    "author_url": "http://magdalapbnmq.tk",
    "date": "2019-11-12 18:25:12",
    "indent_level": 0,
    "content": "100 free online dating site: \n<a href=\"http://anevaylafze.gq/18-adult-movies-download.html\" rel=\"nofollow\">18 adult movies download</a> <a href=\"http://storeadzw.gq/adult-mini-husky.html\" rel=\"nofollow\">Adult mini husky</a> <a href=\"http://2kamamovie.gq/underwater-porn.html\" rel=\"nofollow\">Underwater porn</a>  - zoltarscard82, 2nd Februrary 2016 \nhttp://storeadzw.gq/free-high-definition-porn-videos.html\n \n<a href=\"http://ycsnreview-o.ga/amateur-porn-mere-france.html\" rel=\"nofollow\">Amateur porn mere france</a>\n<a href=\"http://catunderwearw.ml/kinky-adult-videos.html\" rel=\"nofollow\">Kinky adult videos</a>\n<a href=\"http://rikuku.ml/alby-porno.html\" rel=\"nofollow\">Alby porno</a>\n \nhttp://k-moxreview.ml/m3u-adult-iptv.html"
}
