{
    "id": "174493",
    "author": "dizzainint",
    "author_url": "https://ubjd.ru/cat/interer-kuhni",
    "date": "2019-11-01 02:05:52",
    "indent_level": 0,
    "content": "Обустройство спальни – это не только цвета и текстиль. Необходимо так обустроить покойный и прекрасный интерьер спальни, чтобы в ней дозволено было эффективно расслабиться и набраться сил на грядущий день. \n \nОзнакомьтесь с некоторыми хитростями обустройства красивых интерьеров современной спальни, благодаря которым она довольно оазисом вашей мечты о релаксации и отдыхе! \n \nДля сколько обратить уважение, создавая прекрасный интерьер спальни в современном стиле? \nОбустройство спальни многократно является наиболее ожидаемым моментом присутствие ремонте квартиры. Мы мечтаем о красивом и удобном спальном помещении, только часто последний результат оказывается далеко от созданного в голове образа. \n \nИтак, сколько для нас спальня: \n \nМесто уюта и отдыха. \nПозиция уединения и романтики. \nКаморка с приятной, настраивающей для интим атмосферой. \nКонфиденциальность, уют и тишина. \n \nhttps://ubjd.ru/klassicheskij-interer-spalni-rekomendacii-idei-foto \nhttps://ubjd.ru \n \n<a href=\"https://ubjd.ru/cat/interer-detskoj\" rel=\"nofollow\"> \n \nинтерьер детской комнаты </a>"
}
