{
    "id": "247587",
    "author": "oknaavissu",
    "author_url": "https://avis-okna.su",
    "date": "2020-05-13 19:38:37",
    "indent_level": 0,
    "content": "омпания «АВИС Окна» - продажа и изготовление пластиковых окон \nВ стремительном ритме нового времени, все чаще встает вопрос о комфорте и уюте в доме. Пластиковые окна - идеальное решение. Евроокна избавят Вас не только от шума и пыли города, но и придадут Вашему офису или квартире красоту и респектабельный вид. Сохранить тепло, создать уют, повысить комфорт - все это задачи евроокон. \n \nПроизводители пластиковых окон утверждают, что окна ПВХ задерживают влагу и пыль с улиц. Верить ли им? Можно с уверенностью сказать – ПВХ окна действительно достойны всех тех похвал, которые им воспевают. Надежность и качество изготовления окон не оставляют никаких сомнений. \n \n«АВИС Окна» является официальным дистрибьютором производителя ПВХ профиля – компании Brusbox, что позволяет снизить цену на пластиковые окна. Кроме того мы производим окна ПВХ из марок ведущих производителей ПВХ профиля для пластиковых окон: Rehau, Montblanc. Окна ПВХ по ценам производителя – главная стратегия нашей компании. \n \nСпециалистами компании «АВИС Окна» постоянно проводится контроль изготовления пластиковых окон на предмет соответствия российским гостам и гигиеническим сертификатам. \n \nОкна Rehau, Montblanc, Brusbox – станут украшением в Вашем офисе или квартире. Компания «АВИС Окна» осуществляет весь спектр работ: расчет пластиковых окон, доставка пластиковых окон ПВХ, установка пластиковых окон. \n \nПВХ окна - это легкий выбор уюта в Вашем доме. \nhttps://avis-okna.su \n \n<a href=\"https://avis-okna.su/rehau.html\" rel=\"nofollow\"> пластиковые окна рехау</a>"
}
