{
    "id": "172465",
    "author": "canadianpharmacyndaLes",
    "author_url": "",
    "date": "2019-10-20 09:49:58",
    "indent_level": 0,
    "content": "viagra online canada <a href=\"http://canadianpharmacynda.com/#\" rel=\"nofollow\">canadian pharmacy generic viagra</a> canadian pharmacy viagra generic \n<a href=\"http://canadianpharmacynda.com/#\" rel=\"nofollow\">canadian pharmacy generic viagra</a> \ngeneric viagra canada <a href=\"http://canadianpharmacynda.com/#\" rel=\"nofollow\">viagra online canadian pharmacy</a> canadian pharmacy generic viagra \n<a href=\"http://canadianpharmacynda.com/#\" rel=\"nofollow\">cheap viagra online canadian pharmacy</a>"
}
