{
    "id": "227178",
    "author": "gemmxEmeby",
    "author_url": "https://viagrnetwork.com",
    "date": "2020-04-05 17:22:41",
    "indent_level": 0,
    "content": "thomas drugs-generic viagra  viagra discount coupon  <a href=\"https://viagrnetwork.com/#\" rel=\"nofollow\">viagra side effects  </a>  slipped friend viagra  viagra on netflix \n \ncan i take flomax and viagra at the same time  viagra canada  <a href=\"https://viagrnetwork.com/#\" rel=\"nofollow\">buy viagra online </a>  viagra shelf life potency  vitamins that work like viagra \n \nhttps://viagrnetwork.com/# - how does viagra work"
}
