{
    "id": "233579",
    "author": "juijlyDusly",
    "author_url": "https://www.fresher.ru/elz/",
    "date": "2020-04-19 22:39:46",
    "indent_level": 0,
    "content": "how to make money fast  how does facebook make money  <a href=\"https://www.fresher.ru/elz/#\" rel=\"nofollow\">make money online</a>  homemade items that make money  how to make money blogging \n \nhow to make money from home  ways to make money  <a href=\"https://www.fresher.ru/elz/#\" rel=\"nofollow\"> make money online</a>  make money  diy crafts that make money \n \nhttps://www.fresher.ru/elz/#  - make money online"
}
