{
    "id": "268112",
    "author": "Michaelper",
    "author_url": "https://sexcams00.club",
    "date": "2020-06-08 06:39:42",
    "indent_level": 0,
    "content": "amateur homemade learning about sex with cousin <a href=\"https://amateurwebcams00.xyz\" rel=\"nofollow\">amateurwebcams00</a> amateur forced bj sex. \nasian spread legs butterfly pussy pictures <a href=\"https://asianwebcams00.website\" rel=\"nofollow\">indian sister sex videos </a> asian lesbian hermaphrodite porn. \ninnocent ebony amateur tube <a href=\"https://blackwebcams00.icu\" rel=\"nofollow\">phat black tits and ass </a> black pussy creampie pics. \nnude college girls at party <a href=\"https://collegewebcams00.site\" rel=\"nofollow\">collegewebcams00.site</a> college students caught selling sex korean news. \nlesbian strapon cum party <a href=\"https://lesbianwebcams01.fun\" rel=\"nofollow\">nude girls lesbians comic </a> lesbian sex over omegel. \nmature swallows a cum load <a href=\"https://maturewebcams00.space\" rel=\"nofollow\">mature japanese maiko porn </a> mature hatian pussy brutal fucking. \nnude amatuer boudoir milf in heels <a href=\"https://milfwebcams00.club\" rel=\"nofollow\">milfwebcams00.club</a> big butt milf creampie. \nsweet teen sex photos <a href=\"https://teenwebcams00.uno\" rel=\"nofollow\">young blonde teen nude </a> lesbian sloppy teen ass. \nhard cock close up amateur bedroom <a href=\"https://amateurwebcams00.monster\" rel=\"nofollow\">amateurwebcams00</a> amateur let friend fuck my mature wife. \njapanese teen girls hot spring sex <a href=\"https://asianwebcams00.host\" rel=\"nofollow\">asianwebcams00.host</a> asian mom sexy porn position. \nman sucking big black boobs xxx <a href=\"https://blackwebcams00.pw\" rel=\"nofollow\">blackwebcams00</a> vintage brunette black hat sunbathing porn. \ncollege girlfriend sex air force <a href=\"https://collegewebcams00.store\" rel=\"nofollow\">amateur college porn videos </a> college student gay hairy groped male. \nlesbian trying cock for the first time porn <a href=\"https://lesbianwebcams00.fun\" rel=\"nofollow\">curvy mature lesbian strapon </a> sudanese lesbian with big clits licking. \nfuck mature granny and boy small <a href=\"https://maturewebcams00.club\" rel=\"nofollow\">mature taking huge cock </a> latina bbw mature naked selfie. \nmilf fucked at work <a href=\"https://milfwebcams00.casa\" rel=\"nofollow\">milf gets pussy licked </a> milf in white lingerie. \nnaked teen fucking in frog position compilation <a href=\"https://teenwebcams00.press\" rel=\"nofollow\">teen girl naked selfies </a> teen blonde nude video."
}
