{
    "id": "286080",
    "author": "RickyHog",
    "author_url": "https://personalloans1.site",
    "date": "2020-07-01 02:00:16",
    "indent_level": 0,
    "content": "online casino welcome bonus no deposit <a href=\"https://onlinecasinonodeposit001.com\" rel=\"nofollow\">onlinecasinonodeposit001.com</a> real casino online for real money.  \nhollywood casino online real money <a href=\"https://onlinepokerrealmoney.site\" rel=\"nofollow\">onlinepokerrealmoney.site</a> play online casino games and win real money."
}
