{
    "id": "236321",
    "author": "kktrdEmeby",
    "author_url": "https://pharm-usa-official.com/coronavirus",
    "date": "2020-04-24 10:59:19",
    "indent_level": 0,
    "content": "abbott coronavirus test fda  coronavirus cases  <a href=\"https://pharm-usa-official.com/coronavirus/#\" rel=\"nofollow\">вЂЊвЂЊcoronavirus drug</a>  romney coronavirus negative  worldometer coronavirus \n \ncoronavirus stats  us world coronavirus cases  <a href=\"https://pharm-usa-official.com/coronavirus/#\" rel=\"nofollow\"> coronavirus statistics</a>  italy coronavirus cases higher  boris johnson coronavirus \n \nhttps://pharm-usa-official.com/coronavirus/#  - вЂЊвЂЊbuy coronavirus"
}
