{
    "id": "538",
    "author": "rafinha_5508",
    "author_url": "http://www.blogger.com/profile/11922003109108082537",
    "date": "2010-11-01 15:29:21",
    "indent_level": 0,
    "content": "Gabi, gostei bastante do texto! Espero que vc esteja certo. Eu tbm não perdi completamente as esperanças, afinal, como diz o ditado, essa é a última que morre. Agora vamos torcer para que ela faça algo de bom para todos nós e não só para si mesma, pois, como vc disse, o Brasil é feito de muuuuitas pessoas! E ela está lá não só por ela, e sim por todos! Então agora é torcer e cobrar! E caso isso não aconteça, estou com vc para sair às ruas de cara pintada de verde e amarelo!<br /><br />Beijos!"
}
