{
    "id": "233469",
    "author": "tesumbDusly",
    "author_url": "https://www.fresher.ru/elz/",
    "date": "2020-04-19 17:17:31",
    "indent_level": 0,
    "content": "make money on youtube  how to make extra money from home  <a href=\"https://www.fresher.ru/elz/#\" rel=\"nofollow\">make money online</a>  make money  make money \n \nmake money online fast  how to make money on youtube  <a href=\"https://www.fresher.ru/elz/#\" rel=\"nofollow\"> make money</a>  how much money can i make on social security  best way to make money online \n \nhttps://www.fresher.ru/elz/#  - make money"
}
